README.txt
setup.py
src/mekk/__init__.py
src/mekk.rtm.egg-info/PKG-INFO
src/mekk.rtm.egg-info/SOURCES.txt
src/mekk.rtm.egg-info/dependency_links.txt
src/mekk.rtm.egg-info/entry_points.txt
src/mekk.rtm.egg-info/namespace_packages.txt
src/mekk.rtm.egg-info/not-zip-safe
src/mekk.rtm.egg-info/requires.txt
src/mekk.rtm.egg-info/top_level.txt
src/mekk/rtm/__init__.py
src/mekk/rtm/connect.py
src/mekk/rtm/rtm_client.py
src/mekk/rtm/rtm_connector.py
src/mekk/rtm/exporters/__init__.py
src/mekk/rtm/exporters/csv.py
src/mekk/rtm/exporters/json.py
src/mekk/rtm/helpers/__access__.py
src/mekk/rtm/helpers/__init__.py
src/mekk/rtm/helpers/connect.py
src/mekk/rtm/helpers/run_export.py
src/mekk/rtm/helpers/run_import.py
src/mekk/rtm/helpers/run_move.py
src/mekk/rtm/helpers/run_tag.py
src/mekk/rtm/importers/__init__.py
src/mekk/rtm/importers/nozbe.py
src/mekk/rtm/importers/rtmjson.py