Metadata-Version: 1.0
Name: mekk.rtm
Version: 0.5.0
Summary: RememberTheMilk client API and command line client
Home-page: UNKNOWN
Author: Marcin Kasperski
Author-email: Marcin.Kasperski@mekk.waw.pl
License: LGPL
Keywords: rtm,RememberTheMilk
Platform: UNKNOWN
Classifier: Programming Language :: Python
Classifier: Intended Audience :: Developers
Classifier: Topic :: Software Development :: Libraries :: Python Modules
